[
	{"name": "all", "header": "all pupils", "position": "left", "tooltipText": null, "parent": null, "pupils": 594481, "value": 0.000},
	{"name": "girls", "header": "girls", "position": "left", "tooltipText": "girls", "parent": "all", "pupils": 292039, "value": 0.600},
	{"name": "girls_non-disadvantaged", "header": "non-disadvantaged", "position": "left", "tooltipText": "non-disadvantaged girls", "parent": "girls", "pupils": 203700, "value": 0.900},
	{"name": "girls_non-disadvantaged_Asian", "header": "Asian", "position": "left", "tooltipText": "non-disadvantaged, Asian girls", "parent": "girls_non-disadvantaged", "pupils": 22747, "value": 1.200},
	{"name": "girls_non-disadvantaged_Asian_EAL", "header": "EAL", "position": "left", "tooltipText": "non-disadvantaged, EAL, Asian girls", "parent": "girls_non-disadvantaged_Asian", "pupils": 17605, "value": 1.200},
	{"name": "girls_non-disadvantaged_Asian_EAL_coastal", "header": "coastal", "position": "left", "tooltipText": "non-disadvantaged, EAL, Asian girls who attend school in coastal areas", "parent": "girls_non-disadvantaged_Asian_EAL", "pupils": 609, "value": 1.200},
	{"name": "girls_non-disadvantaged_Asian_EAL_non-coastal", "header": "non-coastal", "position": "right", "tooltipText": "non-disadvantaged, EAL, Asian girls who do not attend school in coastal areas", "parent": "girls_non-disadvantaged_Asian_EAL", "pupils": 16996, "value": 1.200},
	{"name": "girls_non-disadvantaged_Asian_non-EAL", "header": "non-EAL", "position": "right", "tooltipText": "non-disadvantaged, non-EAL, Asian girls", "parent": "girls_non-disadvantaged_Asian", "pupils": 5142, "value": 1.300},
	{"name": "girls_non-disadvantaged_Asian_non-EAL_coastal", "header": "coastal", "position": "left", "tooltipText": "non-disadvantaged, non-EAL, Asian girls who attend school in coastal areas", "parent": "girls_non-disadvantaged_Asian_non-EAL", "pupils": 195, "value": 1.800},
	{"name": "girls_non-disadvantaged_Asian_non-EAL_non-coastal", "header": "non-coastal", "position": "right", "tooltipText": "non-disadvantaged, non-EAL, Asian girls who do not attend school in coastal areas", "parent": "girls_non-disadvantaged_Asian_non-EAL", "pupils": 4947, "value": 1.300},
	{"name": "girls_non-disadvantaged_black", "header": "black", "position": "left", "tooltipText": "non-disadvantaged, black girls", "parent": "girls_non-disadvantaged", "pupils": 8276, "value": 1.100},
	{"name": "girls_non-disadvantaged_black_EAL", "header": "EAL", "position": "left", "tooltipText": "non-disadvantaged, EAL, black girls", "parent": "girls_non-disadvantaged_black", "pupils": 3377, "value": 1.300},
	{"name": "girls_non-disadvantaged_black_EAL_coastal", "header": "coastal", "position": "left", "tooltipText": "non-disadvantaged, EAL, black girls who attend school in coastal areas", "parent": "girls_non-disadvantaged_black_EAL", "pupils": 104, "value": -0.200},
	{"name": "girls_non-disadvantaged_black_EAL_non-coastal", "header": "non-coastal", "position": "right", "tooltipText": "non-disadvantaged, EAL, black girls who do not attend school in coastal areas", "parent": "girls_non-disadvantaged_black_EAL", "pupils": 3273, "value": 1.400},
	{"name": "girls_non-disadvantaged_black_non-EAL", "header": "non-EAL", "position": "right", "tooltipText": "non-disadvantaged, non-EAL, black girls", "parent": "girls_non-disadvantaged_black", "pupils": 4899, "value": 0.900},
	{"name": "girls_non-disadvantaged_black_non-EAL_coastal", "header": "coastal", "position": "left", "tooltipText": "non-disadvantaged, non-EAL, black girls who attend school in coastal areas", "parent": "girls_non-disadvantaged_black_non-EAL", "pupils": 182, "value": 0.600},
	{"name": "girls_non-disadvantaged_black_non-EAL_non-coastal", "header": "non-coastal", "position": "right", "tooltipText": "non-disadvantaged, non-EAL, black girls who do not attend school in coastal areas", "parent": "girls_non-disadvantaged_black_non-EAL", "pupils": 4717, "value": 1.000},
	{"name": "girls_non-disadvantaged_Chinese", "header": "Chinese", "position": "left", "tooltipText": "non-disadvantaged, Chinese girls", "parent": "girls_non-disadvantaged", "pupils": 1039, "value": 2.200},
	{"name": "girls_non-disadvantaged_Chinese_EAL", "header": "EAL", "position": "left", "tooltipText": "non-disadvantaged, EAL, Chinese girls", "parent": "girls_non-disadvantaged_Chinese", "pupils": 818, "value": 2.200},
	{"name": "girls_non-disadvantaged_Chinese_EAL_coastal", "header": "coastal", "position": "left", "tooltipText": "non-disadvantaged, EAL, Chinese girls who attend school in coastal areas", "parent": "girls_non-disadvantaged_Chinese_EAL", "pupils": 104, "value": 2.200},
	{"name": "girls_non-disadvantaged_Chinese_EAL_non-coastal", "header": "non-coastal", "position": "right", "tooltipText": "non-disadvantaged, EAL, Chinese girls who do not attend school in coastal areas", "parent": "girls_non-disadvantaged_Chinese_EAL", "pupils": 714, "value": 2.200},
	{"name": "girls_non-disadvantaged_Chinese_non-EAL", "header": "non-EAL", "position": "right", "tooltipText": "non-disadvantaged, non-EAL, Chinese girls", "parent": "girls_non-disadvantaged_Chinese", "pupils": 221, "value": 2.000},
	{"name": "girls_non-disadvantaged_Chinese_non-EAL_coastal", "header": "coastal", "position": "left", "tooltipText": "non-disadvantaged, non-EAL, Chinese girls who attend school in coastal areas", "parent": "girls_non-disadvantaged_Chinese_non-EAL", "pupils": 28, "value": 0.100},
	{"name": "girls_non-disadvantaged_Chinese_non-EAL_non-coastal", "header": "non-coastal", "position": "right", "tooltipText": "non-disadvantaged, non-EAL, Chinese girls who do not attend school in coastal areas", "parent": "girls_non-disadvantaged_Chinese_non-EAL", "pupils": 193, "value": 2.200},
	{"name": "girls_non-disadvantaged_mixed", "header": "mixed", "position": "left", "tooltipText": "non-disadvantaged, mixed ethnicity girls", "parent": "girls_non-disadvantaged", "pupils": 10450, "value": 1.600},
	{"name": "girls_non-disadvantaged_mixed_EAL", "header": "EAL", "position": "left", "tooltipText": "non-disadvantaged, EAL, mixed ethnicity girls", "parent": "girls_non-disadvantaged_mixed", "pupils": 1902, "value": 2.000},
	{"name": "girls_non-disadvantaged_mixed_EAL_coastal", "header": "coastal", "position": "left", "tooltipText": "non-disadvantaged, EAL, mixed ethnicity girls who attend school in coastal areas", "parent": "girls_non-disadvantaged_mixed_EAL", "pupils": 164, "value": 2.100},
	{"name": "girls_non-disadvantaged_mixed_EAL_non-coastal", "header": "non-coastal", "position": "right", "tooltipText": "non-disadvantaged, EAL, mixed ethnicity girls who do not attend school in coastal areas", "parent": "girls_non-disadvantaged_mixed_EAL", "pupils": 1738, "value": 2.000},
	{"name": "girls_non-disadvantaged_mixed_non-EAL", "header": "non-EAL", "position": "right", "tooltipText": "non-disadvantaged, non-EAL, mixed ethnicity girls", "parent": "girls_non-disadvantaged_mixed", "pupils": 8548, "value": 1.500},
	{"name": "girls_non-disadvantaged_mixed_non-EAL_coastal", "header": "coastal", "position": "left", "tooltipText": "non-disadvantaged, non-EAL, mixed ethnicity girls who attend school in coastal areas", "parent": "girls_non-disadvantaged_mixed_non-EAL", "pupils": 877, "value": 1.200},
	{"name": "girls_non-disadvantaged_mixed_non-EAL_non-coastal", "header": "non-coastal", "position": "right", "tooltipText": "non-disadvantaged, non-EAL, mixed ethnicity girls who do not attend school in coastal areas", "parent": "girls_non-disadvantaged_mixed_non-EAL", "pupils": 7671, "value": 1.500},
	{"name": "girls_non-disadvantaged_white", "header": "white", "position": "left", "tooltipText": "non-disadvantaged, white girls", "parent": "girls_non-disadvantaged", "pupils": 161188, "value": 0.800},
	{"name": "girls_non-disadvantaged_white_EAL", "header": "EAL", "position": "left", "tooltipText": "non-disadvantaged, EAL, white girls", "parent": "girls_non-disadvantaged_white", "pupils": 11829, "value": 2.100},
	{"name": "girls_non-disadvantaged_white_EAL_coastal", "header": "coastal", "position": "left", "tooltipText": "non-disadvantaged, EAL, white girls who attend school in coastal areas", "parent": "girls_non-disadvantaged_white_EAL", "pupils": 1163, "value": 1.800},
	{"name": "girls_non-disadvantaged_white_EAL_non-coastal", "header": "non-coastal", "position": "right", "tooltipText": "non-disadvantaged, EAL, white girls who do not attend school in coastal areas", "parent": "girls_non-disadvantaged_white_EAL", "pupils": 10666, "value": 2.100},
	{"name": "girls_non-disadvantaged_white_non-EAL", "header": "non-EAL", "position": "right", "tooltipText": "non-disadvantaged, non-EAL, white girls", "parent": "girls_non-disadvantaged_white", "pupils": 149359, "value": 0.700},
	{"name": "girls_non-disadvantaged_white_non-EAL_coastal", "header": "coastal", "position": "left", "tooltipText": "non-disadvantaged, non-EAL, white girls who attend school in coastal areas", "parent": "girls_non-disadvantaged_white_non-EAL", "pupils": 26327, "value": 0.600},
	{"name": "girls_non-disadvantaged_white_non-EAL_non-coastal", "header": "non-coastal", "position": "right", "tooltipText": "non-disadvantaged, non-EAL, white girls who do not attend school in coastal areas", "parent": "girls_non-disadvantaged_white_non-EAL", "pupils": 123032, "value": 0.800},
	{"name": "girls_disadvantaged", "header": "disadvantaged", "position": "right", "tooltipText": "disadvantaged girls", "parent": "girls", "pupils": 88339, "value": -0.100},
	{"name": "girls_disadvantaged_Asian", "header": "Asian", "position": "left", "tooltipText": "disadvantaged, Asian girls", "parent": "girls_disadvantaged", "pupils": 9006, "value": 0.700},
	{"name": "girls_disadvantaged_Asian_EAL", "header": "EAL", "position": "left", "tooltipText": "disadvantaged, EAL, Asian girls", "parent": "girls_disadvantaged_Asian", "pupils": 7393, "value": 0.700},
	{"name": "girls_disadvantaged_Asian_EAL_coastal", "header": "coastal", "position": "left", "tooltipText": "disadvantaged, EAL, Asian girls who attend school in coastal areas", "parent": "girls_disadvantaged_Asian_EAL", "pupils": 164, "value": 1.000},
	{"name": "girls_disadvantaged_Asian_EAL_non-coastal", "header": "non-coastal", "position": "right", "tooltipText": "disadvantaged, EAL, Asian girls who do not attend school in coastal areas", "parent": "girls_disadvantaged_Asian_EAL", "pupils": 7229, "value": 0.700},
	{"name": "girls_disadvantaged_Asian_non-EAL", "header": "non-EAL", "position": "right", "tooltipText": "disadvantaged, non-EAL, Asian girls", "parent": "girls_disadvantaged_Asian", "pupils": 1613, "value": 0.800},
	{"name": "girls_disadvantaged_Asian_non-EAL_coastal", "header": "coastal", "position": "left", "tooltipText": "disadvantaged, non-EAL, Asian girls who attend school in coastal areas", "parent": "girls_disadvantaged_Asian_non-EAL", "pupils": 30, "value": 1.100},
	{"name": "girls_disadvantaged_Asian_non-EAL_non-coastal", "header": "non-coastal", "position": "right", "tooltipText": "disadvantaged, non-EAL, Asian girls who do not attend school in coastal areas", "parent": "girls_disadvantaged_Asian_non-EAL", "pupils": 1583, "value": 0.800},
	{"name": "girls_disadvantaged_black", "header": "black", "position": "left", "tooltipText": "disadvantaged, black girls", "parent": "girls_disadvantaged", "pupils": 9012, "value": 0.800},
	{"name": "girls_disadvantaged_black_EAL", "header": "EAL", "position": "left", "tooltipText": "disadvantaged, EAL, black girls", "parent": "girls_disadvantaged_black", "pupils": 4565, "value": 1.100},
	{"name": "girls_disadvantaged_black_EAL_coastal", "header": "coastal", "position": "left", "tooltipText": "disadvantaged, EAL, black girls who attend school in coastal areas", "parent": "girls_disadvantaged_black_EAL", "pupils": 122, "value": 0.600},
	{"name": "girls_disadvantaged_black_EAL_non-coastal", "header": "non-coastal", "position": "right", "tooltipText": "disadvantaged, EAL, black girls who do not attend school in coastal areas", "parent": "girls_disadvantaged_black_EAL", "pupils": 4443, "value": 1.100},
	{"name": "girls_disadvantaged_black_non-EAL", "header": "non-EAL", "position": "right", "tooltipText": "disadvantaged, non-EAL, black girls", "parent": "girls_disadvantaged_black", "pupils": 4447, "value": 0.500},
	{"name": "girls_disadvantaged_black_non-EAL_coastal", "header": "coastal", "position": "left", "tooltipText": "disadvantaged, non-EAL, black girls who attend school in coastal areas", "parent": "girls_disadvantaged_black_non-EAL", "pupils": 118, "value": 0.800},
	{"name": "girls_disadvantaged_black_non-EAL_non-coastal", "header": "non-coastal", "position": "right", "tooltipText": "disadvantaged, non-EAL, black girls who do not attend school in coastal areas", "parent": "girls_disadvantaged_black_non-EAL", "pupils": 4329, "value": 0.500},
	{"name": "girls_disadvantaged_Chinese", "header": "Chinese", "position": "left", "tooltipText": "disadvantaged, Chinese girls", "parent": "girls_disadvantaged", "pupils": 249, "value": 1.300},
	{"name": "girls_disadvantaged_Chinese_EAL", "header": "EAL", "position": "left", "tooltipText": "disadvantaged, EAL, Chinese girls", "parent": "girls_disadvantaged_Chinese", "pupils": 212, "value": 1.600},
	{"name": "girls_disadvantaged_Chinese_EAL_coastal", "header": "coastal", "position": "left", "tooltipText": "disadvantaged, EAL, Chinese girls who attend school in coastal areas", "parent": "girls_disadvantaged_Chinese_EAL", "pupils": 25, "value": 0.900},
	{"name": "girls_disadvantaged_Chinese_EAL_non-coastal", "header": "non-coastal", "position": "right", "tooltipText": "disadvantaged, EAL, Chinese girls who do not attend school in coastal areas", "parent": "girls_disadvantaged_Chinese_EAL", "pupils": 187, "value": 1.700},
	{"name": "girls_disadvantaged_Chinese_non-EAL", "header": "non-EAL*", "position": "right", "tooltipText": "disadvantaged, non-EAL, Chinese girls", "parent": "girls_disadvantaged_Chinese", "pupils": 37, "value": -0.300},
	{"name": "girls_disadvantaged_mixed", "header": "mixed", "position": "left", "tooltipText": "disadvantaged, mixed ethnicity girls", "parent": "girls_disadvantaged", "pupils": 7404, "value": 0.400},
	{"name": "girls_disadvantaged_mixed_EAL", "header": "EAL", "position": "left", "tooltipText": "disadvantaged, EAL, mixed ethnicity girls", "parent": "girls_disadvantaged_mixed", "pupils": 987, "value": 1.000},
	{"name": "girls_disadvantaged_mixed_EAL_coastal", "header": "coastal", "position": "left", "tooltipText": "disadvantaged, EAL, mixed ethnicity girls who attend school in coastal areas", "parent": "girls_disadvantaged_mixed_EAL", "pupils": 70, "value": 0.600},
	{"name": "girls_disadvantaged_mixed_EAL_non-coastal", "header": "non-coastal", "position": "right", "tooltipText": "disadvantaged, EAL, mixed ethnicity girls who do not attend school in coastal areas", "parent": "girls_disadvantaged_mixed_EAL", "pupils": 917, "value": 1.000},
	{"name": "girls_disadvantaged_mixed_non-EAL", "header": "non-EAL", "position": "right", "tooltipText": "disadvantaged, non-EAL, mixed ethnicity girls", "parent": "girls_disadvantaged_mixed", "pupils": 6417, "value": 0.300},
	{"name": "girls_disadvantaged_mixed_non-EAL_coastal", "header": "coastal", "position": "left", "tooltipText": "disadvantaged, non-EAL, mixed ethnicity girls who attend school in coastal areas", "parent": "girls_disadvantaged_mixed_non-EAL", "pupils": 613, "value": 0.400},
	{"name": "girls_disadvantaged_mixed_non-EAL_non-coastal", "header": "non-coastal", "position": "right", "tooltipText": "disadvantaged, non-EAL, mixed ethnicity girls who do not attend school in coastal areas", "parent": "girls_disadvantaged_mixed_non-EAL", "pupils": 5804, "value": 0.300},
	{"name": "girls_disadvantaged_white", "header": "white", "position": "left", "tooltipText": "disadvantaged, white girls", "parent": "girls_disadvantaged", "pupils": 62668, "value": -0.500},
	{"name": "girls_disadvantaged_white_EAL", "header": "EAL", "position": "left", "tooltipText": "disadvantaged, EAL, white girls", "parent": "girls_disadvantaged_white", "pupils": 3360, "value": 0.900},
	{"name": "girls_disadvantaged_white_EAL_coastal", "header": "coastal", "position": "left", "tooltipText": "disadvantaged, EAL, white girls who attend school in coastal areas", "parent": "girls_disadvantaged_white_EAL", "pupils": 311, "value": 0.900},
	{"name": "girls_disadvantaged_white_EAL_non-coastal", "header": "non-coastal", "position": "right", "tooltipText": "disadvantaged, EAL, white girls who do not attend school in coastal areas", "parent": "girls_disadvantaged_white_EAL", "pupils": 3049, "value": 0.900},
	{"name": "girls_disadvantaged_white_non-EAL", "header": "non-EAL", "position": "right", "tooltipText": "disadvantaged, non-EAL, white girls", "parent": "girls_disadvantaged_white", "pupils": 59308, "value": -0.500},
	{"name": "girls_disadvantaged_white_non-EAL_coastal", "header": "coastal", "position": "left", "tooltipText": "disadvantaged, non-EAL, white girls who attend school in coastal areas", "parent": "girls_disadvantaged_white_non-EAL", "pupils": 12996, "value": -0.400},
	{"name": "girls_disadvantaged_white_non-EAL_non-coastal", "header": "non-coastal", "position": "right", "tooltipText": "disadvantaged, non-EAL, white girls who do not attend school in coastal areas", "parent": "girls_disadvantaged_white_non-EAL", "pupils": 46312, "value": -0.600},
	{"name": "boys", "header": "boys", "position": "left", "tooltipText": "boys", "parent": "all", "pupils": 302442, "value": -0.600},
	{"name": "boys_non-disadvantaged", "header": "non-disadvantaged", "position": "left", "tooltipText": "non-disadvantaged boys", "parent": "boys", "pupils": 211978, "value": -0.300},
	{"name": "boys_non-disadvantaged_Asian", "header": "Asian", "position": "left", "tooltipText": "non-disadvantaged, Asian boys", "parent": "boys_non-disadvantaged", "pupils": 23542, "value": 0.200},
	{"name": "boys_non-disadvantaged_Asian_EAL", "header": "EAL", "position": "left", "tooltipText": "non-disadvantaged, EAL, Asian boys", "parent": "boys_non-disadvantaged_Asian", "pupils": 18095, "value": 0.200},
	{"name": "boys_non-disadvantaged_Asian_EAL_coastal", "header": "coastal", "position": "left", "tooltipText": "non-disadvantaged, EAL, Asian boys who attend school in coastal areas", "parent": "boys_non-disadvantaged_Asian_EAL", "pupils": 607, "value": 0.200},
	{"name": "boys_non-disadvantaged_Asian_EAL_non-coastal", "header": "non-coastal", "position": "right", "tooltipText": "non-disadvantaged, EAL, Asian boys who do not attend school in coastal areas", "parent": "boys_non-disadvantaged_Asian_EAL", "pupils": 17488, "value": 0.200},
	{"name": "boys_non-disadvantaged_Asian_non-EAL", "header": "non-EAL", "position": "right", "tooltipText": "non-disadvantaged, non-EAL, Asian boys", "parent": "boys_non-disadvantaged_Asian", "pupils": 5447, "value": 0.200},
	{"name": "boys_non-disadvantaged_Asian_non-EAL_coastal", "header": "coastal", "position": "left", "tooltipText": "non-disadvantaged, non-EAL, Asian boys who attend school in coastal areas", "parent": "boys_non-disadvantaged_Asian_non-EAL", "pupils": 202, "value": 0.500},
	{"name": "boys_non-disadvantaged_Asian_non-EAL_non-coastal", "header": "non-coastal", "position": "right", "tooltipText": "non-disadvantaged, non-EAL, Asian boys who do not attend school in coastal areas", "parent": "boys_non-disadvantaged_Asian_non-EAL", "pupils": 5245, "value": 0.100},
	{"name": "boys_non-disadvantaged_black", "header": "black", "position": "left", "tooltipText": "non-disadvantaged, black boys", "parent": "boys_non-disadvantaged", "pupils": 8132, "value": -0.400},
	{"name": "boys_non-disadvantaged_black_EAL", "header": "EAL", "position": "left", "tooltipText": "non-disadvantaged, EAL, black boys", "parent": "boys_non-disadvantaged_black", "pupils": 3384, "value": -0.100},
	{"name": "boys_non-disadvantaged_black_EAL_coastal", "header": "coastal", "position": "left", "tooltipText": "non-disadvantaged, EAL, black boys who attend school in coastal areas", "parent": "boys_non-disadvantaged_black_EAL", "pupils": 103, "value": -0.700},
	{"name": "boys_non-disadvantaged_black_EAL_non-coastal", "header": "non-coastal", "position": "right", "tooltipText": "non-disadvantaged, EAL, black boys who do not attend school in coastal areas", "parent": "boys_non-disadvantaged_black_EAL", "pupils": 3281, "value": -0.100},
	{"name": "boys_non-disadvantaged_black_non-EAL", "header": "non-EAL", "position": "right", "tooltipText": "non-disadvantaged, non-EAL, black boys", "parent": "boys_non-disadvantaged_black", "pupils": 4748, "value": -0.600},
	{"name": "boys_non-disadvantaged_black_non-EAL_coastal", "header": "coastal", "position": "left", "tooltipText": "non-disadvantaged, non-EAL, black boys who attend school in coastal areas", "parent": "boys_non-disadvantaged_black_non-EAL", "pupils": 164, "value": -0.100},
	{"name": "boys_non-disadvantaged_black_non-EAL_non-coastal", "header": "non-coastal", "position": "right", "tooltipText": "non-disadvantaged, non-EAL, black boys who do not attend school in coastal areas", "parent": "boys_non-disadvantaged_black_non-EAL", "pupils": 4584, "value": -0.600},
	{"name": "boys_non-disadvantaged_Chinese", "header": "Chinese", "position": "left", "tooltipText": "non-disadvantaged, Chinese boys", "parent": "boys_non-disadvantaged", "pupils": 1007, "value": 1.100},
	{"name": "boys_non-disadvantaged_Chinese_EAL", "header": "EAL", "position": "left", "tooltipText": "non-disadvantaged, EAL, Chinese boys", "parent": "boys_non-disadvantaged_Chinese", "pupils": 797, "value": 1.000},
	{"name": "boys_non-disadvantaged_Chinese_EAL_coastal", "header": "coastal", "position": "left", "tooltipText": "non-disadvantaged, EAL, Chinese boys who attend school in coastal areas", "parent": "boys_non-disadvantaged_Chinese_EAL", "pupils": 111, "value": 0.800},
	{"name": "boys_non-disadvantaged_Chinese_EAL_non-coastal", "header": "non-coastal", "position": "right", "tooltipText": "non-disadvantaged, EAL, Chinese boys who do not attend school in coastal areas", "parent": "boys_non-disadvantaged_Chinese_EAL", "pupils": 686, "value": 1.100},
	{"name": "boys_non-disadvantaged_Chinese_non-EAL", "header": "non-EAL", "position": "right", "tooltipText": "non-disadvantaged, non-EAL, Chinese boys", "parent": "boys_non-disadvantaged_Chinese", "pupils": 210, "value": 1.300},
	{"name": "boys_non-disadvantaged_Chinese_non-EAL_coastal", "header": "coastal", "position": "left", "tooltipText": "non-disadvantaged, non-EAL, Chinese boys who attend school in coastal areas", "parent": "boys_non-disadvantaged_Chinese_non-EAL", "pupils": 22, "value": 1.300},
	{"name": "boys_non-disadvantaged_Chinese_non-EAL_non-coastal", "header": "non-coastal", "position": "right", "tooltipText": "non-disadvantaged, non-EAL, Chinese boys who do not attend school in coastal areas", "parent": "boys_non-disadvantaged_Chinese_non-EAL", "pupils": 188, "value": 1.300},
	{"name": "boys_non-disadvantaged_mixed", "header": "mixed", "position": "left", "tooltipText": "non-disadvantaged, mixed ethnicity boys", "parent": "boys_non-disadvantaged", "pupils": 10543, "value": 0.000},
	{"name": "boys_non-disadvantaged_mixed_EAL", "header": "EAL", "position": "left", "tooltipText": "non-disadvantaged, EAL, mixed ethnicity boys", "parent": "boys_non-disadvantaged_mixed", "pupils": 1869, "value": 0.500},
	{"name": "boys_non-disadvantaged_mixed_EAL_coastal", "header": "coastal", "position": "left", "tooltipText": "non-disadvantaged, EAL, mixed ethnicity boys who attend school in coastal areas", "parent": "boys_non-disadvantaged_mixed_EAL", "pupils": 152, "value": 0.200},
	{"name": "boys_non-disadvantaged_mixed_EAL_non-coastal", "header": "non-coastal", "position": "right", "tooltipText": "non-disadvantaged, EAL, mixed ethnicity boys who do not attend school in coastal areas", "parent": "boys_non-disadvantaged_mixed_EAL", "pupils": 1717, "value": 0.500},
	{"name": "boys_non-disadvantaged_mixed_non-EAL", "header": "non-EAL", "position": "right", "tooltipText": "non-disadvantaged, non-EAL, mixed ethnicity boys", "parent": "boys_non-disadvantaged_mixed", "pupils": 8674, "value": -0.100},
	{"name": "boys_non-disadvantaged_mixed_non-EAL_coastal", "header": "coastal", "position": "left", "tooltipText": "non-disadvantaged, non-EAL, mixed ethnicity boys who attend school in coastal areas", "parent": "boys_non-disadvantaged_mixed_non-EAL", "pupils": 964, "value": 0.100},
	{"name": "boys_non-disadvantaged_mixed_non-EAL_non-coastal", "header": "non-coastal", "position": "right", "tooltipText": "non-disadvantaged, non-EAL, mixed ethnicity boys who do not attend school in coastal areas", "parent": "boys_non-disadvantaged_mixed_non-EAL", "pupils": 7710, "value": -0.100},
	{"name": "boys_non-disadvantaged_white", "header": "white", "position": "left", "tooltipText": "non-disadvantaged, white boys", "parent": "boys_non-disadvantaged", "pupils": 168754, "value": -0.400},
	{"name": "boys_non-disadvantaged_white_EAL", "header": "EAL", "position": "left", "tooltipText": "non-disadvantaged, EAL, white boys", "parent": "boys_non-disadvantaged_white", "pupils": 12474, "value": 0.700},
	{"name": "boys_non-disadvantaged_white_EAL_coastal", "header": "coastal", "position": "left", "tooltipText": "non-disadvantaged, EAL, white boys who attend school in coastal areas", "parent": "boys_non-disadvantaged_white_EAL", "pupils": 1244, "value": 0.400},
	{"name": "boys_non-disadvantaged_white_EAL_non-coastal", "header": "non-coastal", "position": "right", "tooltipText": "non-disadvantaged, EAL, white boys who do not attend school in coastal areas", "parent": "boys_non-disadvantaged_white_EAL", "pupils": 11230, "value": 0.700},
	{"name": "boys_non-disadvantaged_white_non-EAL", "header": "non-EAL", "position": "right", "tooltipText": "non-disadvantaged, non-EAL, white boys", "parent": "boys_non-disadvantaged_white", "pupils": 156280, "value": -0.500},
	{"name": "boys_non-disadvantaged_white_non-EAL_coastal", "header": "coastal", "position": "left", "tooltipText": "non-disadvantaged, non-EAL, white boys who attend school in coastal areas", "parent": "boys_non-disadvantaged_white_non-EAL", "pupils": 27577, "value": -0.600},
	{"name": "boys_non-disadvantaged_white_non-EAL_non-coastal", "header": "non-coastal", "position": "right", "tooltipText": "non-disadvantaged, non-EAL, white boys who do not attend school in coastal areas", "parent": "boys_non-disadvantaged_white_non-EAL", "pupils": 128703, "value": -0.500},
	{"name": "boys_disadvantaged", "header": "disadvantaged", "position": "right", "tooltipText": "disadvantaged boys", "parent": "boys", "pupils": 90464, "value": -1.100},
	{"name": "boys_disadvantaged_Asian", "header": "Asian", "position": "left", "tooltipText": "disadvantaged, Asian boys", "parent": "boys_disadvantaged", "pupils": 9496, "value": -0.300},
	{"name": "boys_disadvantaged_Asian_EAL", "header": "EAL", "position": "left", "tooltipText": "disadvantaged, EAL, Asian boys", "parent": "boys_disadvantaged_Asian", "pupils": 7789, "value": -0.300},
	{"name": "boys_disadvantaged_Asian_EAL_coastal", "header": "coastal", "position": "left", "tooltipText": "disadvantaged, EAL, Asian boys who attend school in coastal areas", "parent": "boys_disadvantaged_Asian_EAL", "pupils": 177, "value": 0.300},
	{"name": "boys_disadvantaged_Asian_EAL_non-coastal", "header": "non-coastal", "position": "right", "tooltipText": "disadvantaged, EAL, Asian boys who do not attend school in coastal areas", "parent": "boys_disadvantaged_Asian_EAL", "pupils": 7612, "value": -0.300},
	{"name": "boys_disadvantaged_Asian_non-EAL", "header": "non-EAL", "position": "right", "tooltipText": "disadvantaged, non-EAL, Asian boys", "parent": "boys_disadvantaged_Asian", "pupils": 1707, "value": -0.200},
	{"name": "boys_disadvantaged_Asian_non-EAL_coastal", "header": "coastal", "position": "left", "tooltipText": "disadvantaged, non-EAL, Asian boys who attend school in coastal areas", "parent": "boys_disadvantaged_Asian_non-EAL", "pupils": 50, "value": -0.900},
	{"name": "boys_disadvantaged_Asian_non-EAL_non-coastal", "header": "non-coastal", "position": "right", "tooltipText": "disadvantaged, non-EAL, Asian boys who do not attend school in coastal areas", "parent": "boys_disadvantaged_Asian_non-EAL", "pupils": 1657, "value": -0.200},
	{"name": "boys_disadvantaged_black", "header": "black", "position": "left", "tooltipText": "disadvantaged, black boys", "parent": "boys_disadvantaged", "pupils": 9094, "value": -0.600},
	{"name": "boys_disadvantaged_black_EAL", "header": "EAL", "position": "left", "tooltipText": "disadvantaged, EAL, black boys", "parent": "boys_disadvantaged_black", "pupils": 4739, "value": -0.100},
	{"name": "boys_disadvantaged_black_EAL_coastal", "header": "coastal", "position": "left", "tooltipText": "disadvantaged, EAL, black boys who attend school in coastal areas", "parent": "boys_disadvantaged_black_EAL", "pupils": 110, "value": -0.300},
	{"name": "boys_disadvantaged_black_EAL_non-coastal", "header": "non-coastal", "position": "right", "tooltipText": "disadvantaged, EAL, black boys who do not attend school in coastal areas", "parent": "boys_disadvantaged_black_EAL", "pupils": 4629, "value": -0.100},
	{"name": "boys_disadvantaged_black_non-EAL", "header": "non-EAL", "position": "right", "tooltipText": "disadvantaged, non-EAL, black boys", "parent": "boys_disadvantaged_black", "pupils": 4355, "value": -1.000},
	{"name": "boys_disadvantaged_black_non-EAL_coastal", "header": "coastal", "position": "left", "tooltipText": "disadvantaged, non-EAL, black boys who attend school in coastal areas", "parent": "boys_disadvantaged_black_non-EAL", "pupils": 111, "value": -0.800},
	{"name": "boys_disadvantaged_black_non-EAL_non-coastal", "header": "non-coastal", "position": "right", "tooltipText": "disadvantaged, non-EAL, black boys who do not attend school in coastal areas", "parent": "boys_disadvantaged_black_non-EAL", "pupils": 4244, "value": -1.000},
	{"name": "boys_disadvantaged_Chinese", "header": "Chinese", "position": "left", "tooltipText": "disadvantaged, Chinese boys", "parent": "boys_disadvantaged", "pupils": 246, "value": 0.600},
	{"name": "boys_disadvantaged_Chinese_EAL", "header": "EAL", "position": "left", "tooltipText": "disadvantaged, EAL, Chinese boys", "parent": "boys_disadvantaged_Chinese", "pupils": 214, "value": 0.600},
	{"name": "boys_disadvantaged_Chinese_EAL_coastal", "header": "coastal", "position": "left", "tooltipText": "disadvantaged, EAL, Chinese boys who attend school in coastal areas", "parent": "boys_disadvantaged_Chinese_EAL", "pupils": 29, "value": 1.900},
	{"name": "boys_disadvantaged_Chinese_EAL_non-coastal", "header": "non-coastal", "position": "right", "tooltipText": "disadvantaged, EAL, Chinese boys who do not attend school in coastal areas", "parent": "boys_disadvantaged_Chinese_EAL", "pupils": 185, "value": 0.400},
	{"name": "boys_disadvantaged_Chinese_non-EAL", "header": "non-EAL*", "position": "right", "tooltipText": "disadvantaged, non-EAL, Chinese boys", "parent": "boys_disadvantaged_Chinese", "pupils": 32, "value": 0.300},
	{"name": "boys_disadvantaged_mixed", "header": "mixed", "position": "left", "tooltipText": "disadvantaged, mixed ethnicity boys", "parent": "boys_disadvantaged", "pupils": 7587, "value": -0.900},
	{"name": "boys_disadvantaged_mixed_EAL", "header": "EAL", "position": "left", "tooltipText": "disadvantaged, EAL, mixed ethnicity boys", "parent": "boys_disadvantaged_mixed", "pupils": 1029, "value": -0.300},
	{"name": "boys_disadvantaged_mixed_EAL_coastal", "header": "coastal", "position": "left", "tooltipText": "disadvantaged, EAL, mixed ethnicity boys who attend school in coastal areas", "parent": "boys_disadvantaged_mixed_EAL", "pupils": 81, "value": 0.300},
	{"name": "boys_disadvantaged_mixed_EAL_non-coastal", "header": "non-coastal", "position": "right", "tooltipText": "disadvantaged, EAL, mixed ethnicity boys who do not attend school in coastal areas", "parent": "boys_disadvantaged_mixed_EAL", "pupils": 948, "value": -0.300},
	{"name": "boys_disadvantaged_mixed_non-EAL", "header": "non-EAL", "position": "right", "tooltipText": "disadvantaged, non-EAL, mixed ethnicity boys", "parent": "boys_disadvantaged_mixed", "pupils": 6558, "value": -1.000},
	{"name": "boys_disadvantaged_mixed_non-EAL_coastal", "header": "coastal", "position": "left", "tooltipText": "disadvantaged, non-EAL, mixed ethnicity boys who attend school in coastal areas", "parent": "boys_disadvantaged_mixed_non-EAL", "pupils": 640, "value": -0.700},
	{"name": "boys_disadvantaged_mixed_non-EAL_non-coastal", "header": "non-coastal", "position": "right", "tooltipText": "disadvantaged, non-EAL, mixed ethnicity boys who do not attend school in coastal areas", "parent": "boys_disadvantaged_mixed_non-EAL", "pupils": 5918, "value": -1.100},
	{"name": "boys_disadvantaged_white", "header": "white", "position": "left", "tooltipText": "disadvantaged, white boys", "parent": "boys_disadvantaged", "pupils": 64041, "value": -1.400},
	{"name": "boys_disadvantaged_white_EAL", "header": "EAL", "position": "left", "tooltipText": "disadvantaged, EAL, white boys", "parent": "boys_disadvantaged_white", "pupils": 3564, "value": 0.000},
	{"name": "boys_disadvantaged_white_EAL_coastal", "header": "coastal", "position": "left", "tooltipText": "disadvantaged, EAL, white boys who attend school in coastal areas", "parent": "boys_disadvantaged_white_EAL", "pupils": 342, "value": -0.200},
	{"name": "boys_disadvantaged_white_EAL_non-coastal", "header": "non-coastal", "position": "right", "tooltipText": "disadvantaged, EAL, white boys who do not attend school in coastal areas", "parent": "boys_disadvantaged_white_EAL", "pupils": 3222, "value": 0.100},
	{"name": "boys_disadvantaged_white_non-EAL", "header": "non-EAL", "position": "right", "tooltipText": "disadvantaged, non-EAL, white boys", "parent": "boys_disadvantaged_white", "pupils": 60477, "value": -1.500},
	{"name": "boys_disadvantaged_white_non-EAL_coastal", "header": "coastal", "position": "left", "tooltipText": "disadvantaged, non-EAL, white boys who attend school in coastal areas", "parent": "boys_disadvantaged_white_non-EAL", "pupils": 13214, "value": -1.300},
	{"name": "boys_disadvantaged_white_non-EAL_non-coastal", "header": "non-coastal", "position": "right", "tooltipText": "disadvantaged, non-EAL, white boys who do not attend school in coastal areas", "parent": "boys_disadvantaged_white_non-EAL", "pupils": 47263, "value": -1.500}
]
